conversate/__init__.py
conversate/admin.py
conversate/decorators.py
conversate/forms.py
conversate/models.py
conversate/settings.py
conversate/urls.py
conversate/utils.py
conversate/views.py
conversate/migrations/0001_initial.py
conversate/migrations/0002_auto_20181120_0655.py
conversate/migrations/0003_message_file.py
conversate/migrations/__init__.py
conversate/static/conversate/css/styles.css
conversate/static/conversate/images/icons.png
conversate/static/conversate/js/room.js
conversate/templates/conversate/base.html
conversate/templates/conversate/index.html
conversate/templates/conversate/room.html
conversate/templates/conversate/includes/room_input.html
conversate/templates/conversate/includes/room_messages.html
conversate/templates/conversate/includes/room_sidebar.html
conversate/templatetags/__init__.py
conversate/templatetags/conversate.py
django_conversate-0.3.0.dist-info/LICENSE
django_conversate-0.3.0.dist-info/METADATA
django_conversate-0.3.0.dist-info/WHEEL
django_conversate-0.3.0.dist-info/top_level.txt
django_conversate-0.3.0.dist-info/RECORD
