Metadata-Version: 2.1
Name: django-conversate
Version: 0.3.0
Summary: Persistant chat for Django
Home-page: http://radiac.net/projects/django-conversate/
Author: Richard Terry
Author-email: code@radiac.net
License: BSD
Project-URL: Documentation, http://radiac.net/projects/django-conversate/
Project-URL: Source, https://github.com/radiac/django-conversate
Project-URL: Tracker, https://github.com/radiac/django-conversate/issues
Keywords: django wiki
Platform: UNKNOWN
Classifier: Development Status :: 4 - Beta
Classifier: Environment :: Web Environment
Classifier: License :: OSI Approved :: BSD License
Classifier: Operating System :: OS Independent
Classifier: Programming Language :: Python
Classifier: Programming Language :: Python :: 3
Classifier: Programming Language :: Python :: 3 :: Only
Classifier: Programming Language :: Python :: 3.6
Classifier: Programming Language :: Python :: 3.7
Classifier: Programming Language :: Python :: 3.8
Classifier: Framework :: Django
Classifier: Framework :: Django :: 2.2
Requires-Python: >=3.6
Requires-Dist: Django (>=2.2)
Requires-Dist: django-yaa-settings
Requires-Dist: commonmark
Requires-Dist: emoji
